README.md
setup.py
pymacaron_unit/__init__.py
pymacaron_unit/testcase.py
pymacaron_unit.egg-info/PKG-INFO
pymacaron_unit.egg-info/SOURCES.txt
pymacaron_unit.egg-info/dependency_links.txt
pymacaron_unit.egg-info/not-zip-safe
pymacaron_unit.egg-info/requires.txt
pymacaron_unit.egg-info/top_level.txt
test/test_pep8.py
test/test_unit.py