Metadata-Version: 2.1
Name: pymacaron-unit
Version: 1.0.15
Summary: Library for unittesting json REST apis built with pymacaron
Home-page: https://github.com/pymacaron/pymacaron-unit
Author: Erwan Lemonnier
Author-email: erwan@lemonnier.se
License: BSD
Platform: any
Classifier: Environment :: Web Environment
Classifier: Intended Audience :: Developers
Classifier: License :: OSI Approved :: BSD License
Classifier: Operating System :: OS Independent
Classifier: Programming Language :: Python
Classifier: Topic :: Software Development :: Libraries :: Python Modules
